blues_lib/.DS_Store
blues_lib/__init__.py
blues_lib/ability/AbilityExecutor.py
blues_lib/ability/AbilityFacade.py
blues_lib/ability/__init__.py
blues_lib/ability/atom/AtomFacade.py
blues_lib/ability/atom/BaseAbility.py
blues_lib/ability/atom/__init__.py
blues_lib/ability/atom/api/__init__.py
blues_lib/ability/atom/llm/LLMAbilityDict.py
blues_lib/ability/atom/llm/LLMClient.py
blues_lib/ability/atom/llm/__init__.py
blues_lib/ability/atom/matcher/AbilityMatcherFacade.py
blues_lib/ability/atom/matcher/ElementAttributeMatcher.py
blues_lib/ability/atom/matcher/ElementCountMatcher.py
blues_lib/ability/atom/matcher/ElementStateMatcher.py
blues_lib/ability/atom/matcher/ElementTextMatcher.py
blues_lib/ability/atom/matcher/ElementValueMatcher.py
blues_lib/ability/atom/matcher/MatcherAbility.py
blues_lib/ability/atom/matcher/MatcherAbilityDict.py
blues_lib/ability/atom/matcher/UrlMatcher.py
blues_lib/ability/atom/matcher/__init__.py
blues_lib/ability/atom/sql/__init__.py
blues_lib/ability/atom/tool/Dummy.py
blues_lib/ability/atom/tool/ToolAbilityDict.py
blues_lib/ability/atom/tool/Util.py
blues_lib/ability/atom/tool/__init__.py
blues_lib/ability/atom/webdriver/DriverAbility.py
blues_lib/ability/atom/webdriver/DriverAbilityDict.py
blues_lib/ability/atom/webdriver/DriverAbilityFacade.py
blues_lib/ability/atom/webdriver/DriverSearcher.py
blues_lib/ability/atom/webdriver/LocatorCreator.py
blues_lib/ability/atom/webdriver/__init__.py
blues_lib/ability/atom/webdriver/action/Keyboard.py
blues_lib/ability/atom/webdriver/action/Mouse.py
blues_lib/ability/atom/webdriver/action/Wheel.py
blues_lib/ability/atom/webdriver/action/__init__.py
blues_lib/ability/atom/webdriver/action/keyboard/KeyboardArrow.py
blues_lib/ability/atom/webdriver/action/keyboard/KeyboardBase.py
blues_lib/ability/atom/webdriver/action/keyboard/KeyboardHotkey.py
blues_lib/ability/atom/webdriver/action/keyboard/KeyboardSingle.py
blues_lib/ability/atom/webdriver/action/keyboard/OSKeys.py
blues_lib-1.11.3.dist-info/WHEEL
blues_lib-1.11.3.dist-info/METADATA
blues_lib-1.11.3.dist-info/RECORD
