Metadata-Version: 2.3
Name: blues-lib
Version: 1.11.3
Summary: Blues's core library
Author: Blues Liu
Author-email: Blues Liu <1121557826@qq.com>
Requires-Dist: pillow>=10.3.0
Requires-Dist: requests>=2.31.0
Requires-Dist: selenium>=4.25.0
Requires-Dist: tld==0.13
Requires-Dist: pymysql==1.0.2
Requires-Dist: beautifulsoup4==4.9.3
Requires-Dist: pyperclip==1.9.0
Requires-Dist: undetected-chromedriver==3.5.5
Requires-Dist: pyyaml==6.0.2
Requires-Dist: pytest==8.3.5
Requires-Dist: pytest-html==4.1.1
Requires-Dist: jsonschema==4.21.1
Requires-Dist: json5==0.12.0
Requires-Dist: pyhocon==0.3.61
Requires-Dist: tiktoken>=0.5.1
Requires-Dist: pytest-bdd>=8.1.0
Requires-Dist: openai>=2.3.0
Requires-Dist: python-dotenv>=1.1.1
Requires-Dist: setuptools>=80.9.0
Requires-Dist: mergedeep>=1.3.4
Requires-Python: >=3.11
Provides-Extra: dev
